{"entityType":"unified","colorField":"nodeType","nodes":[{"id":"species-10015","label":"lion","nodeType":"species","kingdom":"Animalia","family":null,"degree":3,"size":2.6090354888959126,"x":-12.948050498962402,"y":30.9421329498291,"community":53,"communityLabel":"Denver, rehabilitation, lion"},{"id":"concept-10090","label":"commercial exploitation","nodeType":"concept","scope":"conservation","conceptType":"threat","degree":4,"size":2.7875503299472806,"x":-4.0365495681762695,"y":17.445507049560547,"community":53,"communityLabel":"Denver, rehabilitation, lion"},{"id":"concept-10119","label":"trench excavation","nodeType":"concept","scope":"water_resources","conceptType":"process","degree":51,"size":4.660994974865142,"x":38.61106872558594,"y":4.047168731689453,"community":53,"communityLabel":"Denver, rehabilitation, lion"},{"id":"concept-10120","label":"pretreatment","nodeType":"concept","scope":"water_resources","conceptType":"process","degree":5,"size":2.933407575382444,"x":31.282270431518555,"y":10.996797561645508,"community":53,"communityLabel":"Denver, rehabilitation, lion"},{"id":"concept-9690","label":"loose snow avalanches","nodeType":"concept","scope":"general_ecology","conceptType":"phenomenon","degree":31,"size":4.272588722239782,"x":-12.160130500793457,"y":-32.70627975463867,"community":53,"communityLabel":"Denver, rehabilitation, lion"},{"id":"concept-10194","label":"National Energy Conservation Challenge","nodeType":"concept","scope":"energy","conceptType":"policy","degree":9,"size":3.342068074395237,"x":27.795108795166016,"y":-20.898067474365234,"community":53,"communityLabel":"Denver, rehabilitation, lion"},{"id":"concept-10195","label":"voluntary conservation program","nodeType":"concept","scope":"energy","conceptType":"policy","degree":9,"size":3.342068074395237,"x":25.046117782592773,"y":-17.62550163269043,"community":53,"communityLabel":"Denver, rehabilitation, lion"},{"id":"concept-10203","label":"cleanup standards","nodeType":"concept","scope":"environmental_review","conceptType":"regulation","degree":11,"size":3.4879253198304,"x":-29.19405174255371,"y":6.882236480712891,"community":53,"communityLabel":"Denver, rehabilitation, lion"},{"id":"concept-10378","label":"rehabilitation","nodeType":"concept","scope":"mining","conceptType":"process","degree":78,"size":4.995558281973617,"x":15.85010051727295,"y":7.884883403778076,"community":53,"communityLabel":"Denver, rehabilitation, lion"},{"id":"concept-10466","label":"circulation plan","nodeType":"concept","scope":"community_planning","conceptType":"framework","degree":4,"size":2.7875503299472806,"x":30.015600204467773,"y":-29.84507179260254,"community":53,"communityLabel":"Denver, rehabilitation, lion"},{"id":"concept-10541","label":"H.B. 1041","nodeType":"concept","scope":"land_use","conceptType":"regulation","degree":26,"size":4.136669492803463,"x":24.069570541381836,"y":10.989212989807129,"community":53,"communityLabel":"Denver, rehabilitation, lion"},{"id":"concept-10557","label":"C-S program","nodeType":"concept","scope":"community_planning","conceptType":"framework","degree":5,"size":2.933407575382444,"x":-7.014372825622559,"y":-30.612842559814453,"community":53,"communityLabel":"Denver, rehabilitation, lion"},{"id":"concept-10784","label":"A-95 process","nodeType":"concept","scope":"community_planning","conceptType":"policy","degree":6,"size":3.0567281192442506,"x":3.4758460521698,"y":-32.09847640991211,"community":53,"communityLabel":"Denver, rehabilitation, lion"},{"id":"concept-10995","label":"non injury doctrine","nodeType":"concept","scope":"water_resources","conceptType":"regulation","degree":12,"size":3.5519594859692294,"x":29.79960823059082,"y":0.489424467086792,"community":53,"communityLabel":"Denver, rehabilitation, lion"},{"id":"concept-11085","label":"permanent injunction","nodeType":"concept","scope":"water_resources","conceptType":"regulation","degree":5,"size":2.933407575382444,"x":-8.922978401184082,"y":27.13677406311035,"community":53,"communityLabel":"Denver, rehabilitation, lion"},{"id":"concept-11102","label":"impact assistance","nodeType":"concept","scope":"community_planning","conceptType":"policy","degree":5,"size":2.933407575382444,"x":-3.103732109069824,"y":-35.343074798583984,"community":53,"communityLabel":"Denver, rehabilitation, lion"},{"id":"concept-11354","label":"tunnel construction","nodeType":"concept","scope":"engineering","conceptType":"process","degree":3,"size":2.6090354888959126,"x":-14.027528762817383,"y":-47.69696044921875,"community":53,"communityLabel":"Denver, rehabilitation, lion"},{"id":"place-8046","label":"Aurora, CO","nodeType":"place","placeType":"town","scale":null,"degree":4,"size":2.7875503299472806,"x":14.116793632507324,"y":-1.9191440343856812,"community":53,"communityLabel":"Denver, rehabilitation, lion"},{"id":"place-8278","label":"Denver Federal Center","nodeType":"place","placeType":"study_site","scale":null,"degree":35,"size":4.366815150764888,"x":4.580960750579834,"y":-30.921295166015625,"community":53,"communityLabel":"Denver, rehabilitation, lion"},{"id":"place-8313","label":"Edinburgh","nodeType":"place","placeType":"town","scale":null,"degree":3,"size":2.6090354888959126,"x":-11.95564079284668,"y":25.118223190307617,"community":53,"communityLabel":"Denver, rehabilitation, lion"},{"id":"place-8534","label":"Moffat Tunnel","nodeType":"place","placeType":"other","scale":null,"degree":8,"size":3.257779661868976,"x":16.857873916625977,"y":22.691267013549805,"community":53,"communityLabel":"Denver, rehabilitation, lion"},{"id":"place-8890","label":"Burlington","nodeType":"place","placeType":"town","scale":null,"degree":29,"size":4.220957905329724,"x":27.046472549438477,"y":-6.6234846115112305,"community":53,"communityLabel":"Denver, rehabilitation, lion"},{"id":"place-9368","label":"Roosevelt","nodeType":"place","placeType":"mine","scale":null,"degree":6,"size":3.0567281192442506,"x":-37.06376647949219,"y":23.523191452026367,"community":53,"communityLabel":"Denver, rehabilitation, lion"},{"id":"place-10273","label":"Westcliffe","nodeType":"place","placeType":"town","scale":null,"degree":4,"size":2.7875503299472806,"x":-5.7115302085876465,"y":32.96592712402344,"community":53,"communityLabel":"Denver, rehabilitation, lion"},{"id":"place-10659","label":"Piney Lake","nodeType":"place","placeType":"lake","scale":null,"degree":6,"size":3.0567281192442506,"x":37.1707878112793,"y":-43.26614761352539,"community":53,"communityLabel":"Denver, rehabilitation, lion"},{"id":"place-11876","label":"Puget Sound","nodeType":"place","placeType":"lake","scale":null,"degree":7,"size":3.163553233343869,"x":-4.9789299964904785,"y":26.78978157043457,"community":53,"communityLabel":"Denver, rehabilitation, lion"},{"id":"place-7838","label":"Waunita Hot Springs","nodeType":"place","placeType":"stream","scale":null,"degree":15,"size":3.718070977791825,"x":-21.255794525146484,"y":26.007831573486328,"community":53,"communityLabel":"Denver, rehabilitation, lion"},{"id":"place-7846","label":"College Station","nodeType":"place","placeType":"town","scale":null,"degree":3,"size":2.6090354888959126,"x":-23.64545249938965,"y":27.80658531188965,"community":53,"communityLabel":"Denver, rehabilitation, lion"},{"id":"place-7867","label":"California Gulch","nodeType":"place","placeType":"valley","scale":null,"degree":9,"size":3.342068074395237,"x":-52.85578155517578,"y":5.886906147003174,"community":53,"communityLabel":"Denver, rehabilitation, lion"},{"id":"place-8196","label":"Salem","nodeType":"place","placeType":"town","scale":null,"degree":19,"size":3.8965858188431928,"x":12.674277305603027,"y":12.52698802947998,"community":53,"communityLabel":"Denver, rehabilitation, lion"},{"id":"place-8200","label":"Topeka","nodeType":"place","placeType":"town","scale":null,"degree":3,"size":2.6090354888959126,"x":-40.61258316040039,"y":10.779041290283203,"community":53,"communityLabel":"Denver, rehabilitation, lion"},{"id":"place-6505","label":"Denver","nodeType":"place","placeType":"town","scale":null,"degree":2837,"size":7.860683886175991,"x":11.61808967590332,"y":7.778937339782715,"community":53,"communityLabel":"Denver, rehabilitation, lion"},{"id":"place-7448","label":"Helena","nodeType":"place","placeType":"town","scale":null,"degree":26,"size":4.136669492803463,"x":-6.743328094482422,"y":2.175741672515869,"community":53,"communityLabel":"Denver, rehabilitation, lion"},{"id":"place-7799","label":"Stapleton International Airport","nodeType":"place","placeType":"subdivision","scale":null,"degree":4,"size":2.7875503299472806,"x":12.229317665100098,"y":19.5249080657959,"community":53,"communityLabel":"Denver, rehabilitation, lion"},{"id":"place-7869","label":"Yak Tunnel","nodeType":"place","placeType":"mine","scale":null,"degree":9,"size":3.342068074395237,"x":-35.85094451904297,"y":19.811002731323242,"community":53,"communityLabel":"Denver, rehabilitation, lion"},{"id":"place-8707","label":"Antonito","nodeType":"place","placeType":"town","scale":null,"degree":6,"size":3.0567281192442506,"x":27.65381622314453,"y":9.886561393737793,"community":53,"communityLabel":"Denver, rehabilitation, lion"},{"id":"place-10045","label":"Lake Dillon","nodeType":"place","placeType":"lake","scale":null,"degree":8,"size":3.257779661868976,"x":12.018988609313965,"y":-15.650495529174805,"community":53,"communityLabel":"Denver, rehabilitation, lion"},{"id":"place-10545","label":"Uncompahgre Primitive Area","nodeType":"place","placeType":"wilderness_area","scale":null,"degree":4,"size":2.7875503299472806,"x":4.448047637939453,"y":-10.133480072021484,"community":53,"communityLabel":"Denver, rehabilitation, lion"},{"id":"place-11045","label":"Alta","nodeType":"place","placeType":"town","scale":null,"degree":12,"size":3.5519594859692294,"x":-21.272180557250977,"y":-70.73191833496094,"community":53,"communityLabel":"Denver, rehabilitation, lion"},{"id":"stakeholder-1141","label":"county sheriff","nodeType":"stakeholder","stakeholderType":"local_gov","degree":2,"size":2.3788898309344875,"x":31.175050735473633,"y":62.97228240966797,"community":53,"communityLabel":"Denver, rehabilitation, lion"},{"id":"author-28281","label":"R. G. Clark","nodeType":"author","degree":63,"size":4.827106466687738,"x":11.823578834533691,"y":-9.69940185546875,"community":16,"communityLabel":"air quality monitoring, Mt. Washington, caribou"},{"id":"document-3207","label":"Environmentalist Forced to Break Dam","nodeType":"document","documentType":"news_article","degree":2,"size":2.3788898309344875,"x":-39.927513122558594,"y":-25.014493942260742,"community":53,"communityLabel":"Denver, rehabilitation, lion"},{"id":"document-3671","label":"Proposition 3, the Nuclear Safeguards Initiative, ","nodeType":"document","documentType":"correspondence","degree":5,"size":2.933407575382444,"x":4.255566120147705,"y":-29.103248596191406,"community":53,"communityLabel":"Denver, rehabilitation, lion"},{"id":"document-4133","label":"Winter Recreation Safety Guide","nodeType":"document","documentType":"recreation_study","degree":32,"size":4.297206049173184,"x":-16.26662826538086,"y":-34.511898040771484,"community":53,"communityLabel":"Denver, rehabilitation, lion"},{"id":"story-5496","label":"Request to participate in Snodgrass  appeal denied","nodeType":"story","storyType":"news_article","degree":2,"size":2.3788898309344875,"x":-24.144947052001953,"y":38.21003723144531,"community":53,"communityLabel":"Denver, rehabilitation, lion"}],"edges":[{"source":"concept-9690","target":"place-6505","weight":3},{"source":"concept-10090","target":"place-6505","weight":2},{"source":"concept-10119","target":"concept-10120","weight":2},{"source":"concept-10119","target":"place-6505","weight":5},{"source":"concept-10120","target":"place-6505","weight":2},{"source":"concept-10194","target":"concept-10195","weight":2},{"source":"concept-10194","target":"place-6505","weight":2},{"source":"concept-10195","target":"place-6505","weight":2},{"source":"concept-10203","target":"place-6505","weight":3},{"source":"concept-10203","target":"place-7867","weight":2},{"source":"concept-10203","target":"place-7869","weight":2},{"source":"concept-10378","target":"place-6505","weight":5},{"source":"concept-10378","target":"place-8534","weight":2},{"source":"concept-10466","target":"place-6505","weight":2},{"source":"concept-10541","target":"concept-10995","weight":2},{"source":"concept-10541","target":"place-6505","weight":5},{"source":"concept-10557","target":"place-6505","weight":2},{"source":"concept-10784","target":"place-6505","weight":2},{"source":"concept-10995","target":"place-6505","weight":2},{"source":"concept-11085","target":"place-6505","weight":2},{"source":"concept-11102","target":"place-6505","weight":2},{"source":"concept-11354","target":"place-6505","weight":2},{"source":"place-6505","target":"place-7448","weight":4},{"source":"place-6505","target":"place-7799","weight":2},{"source":"place-6505","target":"place-7838","weight":4},{"source":"place-6505","target":"place-7846","weight":2},{"source":"place-6505","target":"place-7867","weight":2},{"source":"place-6505","target":"place-7869","weight":2},{"source":"place-6505","target":"place-8046","weight":2},{"source":"place-6505","target":"place-8196","weight":3},{"source":"place-6505","target":"place-8200","weight":2},{"source":"place-6505","target":"place-8278","weight":5},{"source":"place-6505","target":"place-8313","weight":2},{"source":"place-6505","target":"place-8534","weight":2},{"source":"place-6505","target":"place-8707","weight":2},{"source":"place-6505","target":"place-8890","weight":4},{"source":"place-6505","target":"place-9368","weight":2},{"source":"place-6505","target":"place-10045","weight":2},{"source":"place-6505","target":"place-10273","weight":2},{"source":"place-6505","target":"place-10545","weight":2},{"source":"place-6505","target":"place-10659","weight":2},{"source":"place-6505","target":"place-11045","weight":3},{"source":"place-6505","target":"place-11876","weight":3},{"source":"place-6505","target":"species-10015","weight":2},{"source":"place-7867","target":"place-7869","weight":2},{"source":"author-28281","target":"place-6505","weight":5},{"source":"author-28281","target":"place-8278","weight":2},{"source":"document-4133","target":"concept-9690","weight":1},{"source":"document-3671","target":"place-6505","weight":1},{"source":"document-4133","target":"place-6505","weight":1},{"source":"document-3207","target":"place-6505","weight":1},{"source":"document-4133","target":"place-8278","weight":1},{"source":"document-4133","target":"place-11045","weight":1},{"source":"story-5496","target":"place-6505","weight":1},{"source":"stakeholder-1141","target":"document-4133","weight":1}],"meta":{"nodeCount":45,"edgeCount":55}}