{"entityType":"unified","colorField":"nodeType","nodes":[{"id":"species-9088","label":"river otter","nodeType":"species","kingdom":"Animalia","family":null,"degree":218,"size":5.811257383853201,"x":52.412330627441406,"y":48.509925842285156,"community":11,"communityLabel":"San Luis Valley, Canon City, Lontra canadensis"},{"id":"species-9711","label":"spotted owls","nodeType":"species","kingdom":"Animalia","family":null,"degree":157,"size":5.550076026421574,"x":57.93487548828125,"y":43.030208587646484,"community":11,"communityLabel":"San Luis Valley, Canon City, Lontra canadensis"},{"id":"species-9075","label":"grizzlies","nodeType":"species","kingdom":"Animalia","family":null,"degree":11,"size":3.4879253198304,"x":64.75091552734375,"y":21.022497177124023,"community":11,"communityLabel":"San Luis Valley, Canon City, Lontra canadensis"},{"id":"species-9458","label":"Bison","nodeType":"species","kingdom":null,"family":null,"degree":40,"size":4.4708576533634465,"x":-2.585596799850464,"y":69.5110855102539,"community":11,"communityLabel":"San Luis Valley, Canon City, Lontra canadensis"},{"id":"species-9466","label":"osprey","nodeType":"species","kingdom":"Animalia","family":null,"degree":7,"size":3.163553233343869,"x":46.2225227355957,"y":52.33639907836914,"community":11,"communityLabel":"San Luis Valley, Canon City, Lontra canadensis"},{"id":"species-9470","label":"porcupine","nodeType":"species","kingdom":"Animalia","family":null,"degree":45,"size":4.562913117191276,"x":28.893877029418945,"y":21.83080291748047,"community":11,"communityLabel":"San Luis Valley, Canon City, Lontra canadensis"},{"id":"species-10059","label":"chorus frog","nodeType":"species","kingdom":"Animalia","family":null,"degree":56,"size":4.73444101426764,"x":10.176856994628906,"y":22.601381301879883,"community":11,"communityLabel":"San Luis Valley, Canon City, Lontra canadensis"},{"id":"species-8916","label":"Lontra canadensis","nodeType":"species","kingdom":"Animalia","family":"Mustelidae","degree":223,"size":5.829316841484032,"x":98.93336486816406,"y":113.14643859863281,"community":11,"communityLabel":"San Luis Valley, Canon City, Lontra canadensis"},{"id":"species-8963","label":"Lesser Prairie Chicken","nodeType":"species","kingdom":"Animalia","family":null,"degree":78,"size":4.995558281973617,"x":42.970638275146484,"y":31.036170959472656,"community":11,"communityLabel":"San Luis Valley, Canon City, Lontra canadensis"},{"id":"species-8996","label":"greater prairie chicken","nodeType":"species","kingdom":"Animalia","family":null,"degree":9,"size":3.342068074395237,"x":-85.28024291992188,"y":-2.115950107574463,"community":11,"communityLabel":"San Luis Valley, Canon City, Lontra canadensis"},{"id":"species-8990","label":"Mexican spotted owl","nodeType":"species","kingdom":"Animalia","family":null,"degree":94,"size":5.143101513280433,"x":96.38863372802734,"y":-14.039892196655273,"community":11,"communityLabel":"San Luis Valley, Canon City, Lontra canadensis"},{"id":"species-9192","label":"Comarum palustre","nodeType":"species","kingdom":"Plantae","family":"Rosaceae","degree":38,"size":4.430849316903718,"x":-104.8736801147461,"y":-32.960453033447266,"community":11,"communityLabel":"San Luis Valley, Canon City, Lontra canadensis"},{"id":"species-9196","label":"Eriophorum gracile","nodeType":"species","kingdom":"Plantae","family":"Cyperaceae","degree":38,"size":4.430849316903718,"x":-98.77542877197266,"y":-20.865966796875,"community":11,"communityLabel":"San Luis Valley, Canon City, Lontra canadensis"},{"id":"species-9268","label":"southern redbelly dace","nodeType":"species","kingdom":"Animalia","family":null,"degree":11,"size":3.4879253198304,"x":-61.74540328979492,"y":-1.6230652332305908,"community":11,"communityLabel":"San Luis Valley, Canon City, Lontra canadensis"},{"id":"species-9275","label":"Skiff milkvetch","nodeType":"species","kingdom":"Plantae","family":null,"degree":138,"size":5.4475791465045535,"x":66.63711547851562,"y":-65.49267578125,"community":11,"communityLabel":"San Luis Valley, Canon City, Lontra canadensis"},{"id":"species-9462","label":"sharp-tailed grouse","nodeType":"species","kingdom":"Animalia","family":null,"degree":69,"size":4.8987961936394875,"x":22.49435806274414,"y":71.702880859375,"community":11,"communityLabel":"San Luis Valley, Canon City, Lontra canadensis"},{"id":"species-9463","label":"prairie chickens","nodeType":"species","kingdom":"Animalia","family":null,"degree":155,"size":5.5398848057996295,"x":31.060901641845703,"y":49.53657913208008,"community":11,"communityLabel":"San Luis Valley, Canon City, Lontra canadensis"},{"id":"species-9521","label":"snowy egrets","nodeType":"species","kingdom":"Animalia","family":null,"degree":32,"size":4.297206049173184,"x":18.039962768554688,"y":15.659615516662598,"community":11,"communityLabel":"San Luis Valley, Canon City, Lontra canadensis"},{"id":"species-9712","label":"marbled murrelets","nodeType":"species","kingdom":"Animalia","family":null,"degree":4,"size":2.7875503299472806,"x":103.3218765258789,"y":-34.786033630371094,"community":11,"communityLabel":"San Luis Valley, Canon City, Lontra canadensis"},{"id":"species-9903","label":"Northern Spotted Owl","nodeType":"species","kingdom":"Animalia","family":null,"degree":11,"size":3.4879253198304,"x":96.94232177734375,"y":88.18828582763672,"community":11,"communityLabel":"San Luis Valley, Canon City, Lontra canadensis"},{"id":"species-10042","label":"Egretta thula","nodeType":"species","kingdom":"Animalia","family":"Ardeidae","degree":56,"size":4.73444101426764,"x":-29.120677947998047,"y":3.968258857727051,"community":11,"communityLabel":"San Luis Valley, Canon City, Lontra canadensis"},{"id":"species-10044","label":"Nycticorax nycticorax","nodeType":"species","kingdom":"Animalia","family":"Ardeidae","degree":24,"size":4.075100659894561,"x":-53.26602554321289,"y":-41.254581451416016,"community":11,"communityLabel":"San Luis Valley, Canon City, Lontra canadensis"},{"id":"species-10943","label":"Ophiomorpha","nodeType":"species","kingdom":null,"family":null,"degree":48,"size":4.613456238488501,"x":58.387638092041016,"y":-35.09605026245117,"community":11,"communityLabel":"San Luis Valley, Canon City, Lontra canadensis"},{"id":"species-10944","label":"Trichichnus","nodeType":"species","kingdom":null,"family":null,"degree":47,"size":4.596960808726313,"x":-2.2745773792266846,"y":-10.853072166442871,"community":11,"communityLabel":"San Luis Valley, Canon City, Lontra canadensis"},{"id":"species-10945","label":"Thalassinoides","nodeType":"species","kingdom":null,"family":null,"degree":47,"size":4.596960808726313,"x":56.804412841796875,"y":-8.667553901672363,"community":11,"communityLabel":"San Luis Valley, Canon City, Lontra canadensis"},{"id":"species-10946","label":"Arenicolites","nodeType":"species","kingdom":null,"family":null,"degree":47,"size":4.596960808726313,"x":-40.28008270263672,"y":-151.8389892578125,"community":11,"communityLabel":"San Luis Valley, Canon City, Lontra canadensis"},{"id":"species-10947","label":"Asterosoma","nodeType":"species","kingdom":null,"family":null,"degree":47,"size":4.596960808726313,"x":53.791297912597656,"y":-45.01140594482422,"community":11,"communityLabel":"San Luis Valley, Canon City, Lontra canadensis"},{"id":"species-10948","label":"Teichichnus","nodeType":"species","kingdom":null,"family":null,"degree":47,"size":4.596960808726313,"x":51.10020446777344,"y":-118.2641372680664,"community":11,"communityLabel":"San Luis Valley, Canon City, Lontra canadensis"},{"id":"species-10949","label":"Skolithos","nodeType":"species","kingdom":null,"family":null,"degree":47,"size":4.596960808726313,"x":-0.5625554919242859,"y":-83.09991455078125,"community":11,"communityLabel":"San Luis Valley, Canon City, Lontra canadensis"},{"id":"species-10950","label":"Planolites","nodeType":"species","kingdom":null,"family":null,"degree":47,"size":4.596960808726313,"x":62.81352996826172,"y":-42.84842300415039,"community":11,"communityLabel":"San Luis Valley, Canon City, Lontra canadensis"},{"id":"species-10952","label":"Diplodocus","nodeType":"species","kingdom":"Animalia","family":null,"degree":24,"size":4.075100659894561,"x":-69.48219299316406,"y":-31.52303695678711,"community":11,"communityLabel":"San Luis Valley, Canon City, Lontra canadensis"},{"id":"concept-8641","label":"strontium isotope tracing","nodeType":"concept","scope":"biogeochemistry","conceptType":"measurement","degree":2,"size":2.3788898309344875,"x":56.39573669433594,"y":-74.9930648803711,"community":11,"communityLabel":"San Luis Valley, Canon City, Lontra canadensis"},{"id":"concept-9789","label":"Closed Basin Division","nodeType":"concept","scope":"water_resources","conceptType":"framework","degree":3,"size":2.6090354888959126,"x":-136.90045166015625,"y":-45.44586181640625,"community":11,"communityLabel":"San Luis Valley, Canon City, Lontra canadensis"},{"id":"concept-10147","label":"paleoecology","nodeType":"concept","scope":"general_ecology","conceptType":"framework","degree":135,"size":5.4301239085888415,"x":-0.9259799122810364,"y":-2.429004430770874,"community":11,"communityLabel":"San Luis Valley, Canon City, Lontra canadensis"},{"id":"concept-10603","label":"UDAG funds","nodeType":"concept","scope":"community_planning","conceptType":"policy","degree":13,"size":3.6112458636922073,"x":-10.259967803955078,"y":128.5703582763672,"community":11,"communityLabel":"San Luis Valley, Canon City, Lontra canadensis"},{"id":"concept-10654","label":"sage grouse habitat enhancement","nodeType":"concept","scope":"wildlife","conceptType":"process","degree":6,"size":3.0567281192442506,"x":66.90565490722656,"y":-50.81708908081055,"community":11,"communityLabel":"San Luis Valley, Canon City, Lontra canadensis"},{"id":"concept-11532","label":"dissolved As","nodeType":"concept","scope":"biogeochemistry","conceptType":"measurement","degree":2,"size":2.3788898309344875,"x":-98.80325317382812,"y":36.93375778198242,"community":11,"communityLabel":"San Luis Valley, Canon City, Lontra canadensis"},{"id":"place-6741","label":"San Luis Valley","nodeType":"place","placeType":"valley","scale":null,"degree":969,"size":7.001836857197944,"x":-59.36717224121094,"y":31.118824005126953,"community":11,"communityLabel":"San Luis Valley, Canon City, Lontra canadensis"},{"id":"place-6744","label":"Del Norte","nodeType":"place","placeType":"town","scale":null,"degree":26,"size":4.136669492803463,"x":-42.0616340637207,"y":8.81619644165039,"community":11,"communityLabel":"San Luis Valley, Canon City, Lontra canadensis"},{"id":"place-6745","label":"Center","nodeType":"place","placeType":"town","scale":null,"degree":28,"size":4.193836663989179,"x":-94.57823181152344,"y":-35.77947998046875,"community":11,"communityLabel":"San Luis Valley, Canon City, Lontra canadensis"},{"id":"place-7202","label":"Redstone","nodeType":"place","placeType":"town","scale":null,"degree":2,"size":2.3788898309344875,"x":-98.26093292236328,"y":-49.080650329589844,"community":11,"communityLabel":"San Luis Valley, Canon City, Lontra canadensis"},{"id":"place-7355","label":"Idaho Springs","nodeType":"place","placeType":"town","scale":null,"degree":97,"size":5.1679739829364575,"x":-58.88221740722656,"y":18.944438934326172,"community":11,"communityLabel":"San Luis Valley, Canon City, Lontra canadensis"},{"id":"place-7699","label":"Mt. Baldy","nodeType":"place","placeType":"peak","scale":null,"degree":48,"size":4.613456238488501,"x":-83.6277847290039,"y":26.422271728515625,"community":11,"communityLabel":"San Luis Valley, Canon City, Lontra canadensis"},{"id":"place-7705","label":"Mexican Cut","nodeType":"place","placeType":"valley","scale":null,"degree":8,"size":3.257779661868976,"x":-58.35239028930664,"y":-73.63274383544922,"community":11,"communityLabel":"San Luis Valley, Canon City, Lontra canadensis"},{"id":"place-7707","label":"Mount Evans","nodeType":"place","placeType":"peak","scale":null,"degree":30,"size":4.247189763588118,"x":-12.862222671508789,"y":45.10370635986328,"community":11,"communityLabel":"San Luis Valley, Canon City, Lontra canadensis"},{"id":"place-7721","label":"Paradox Valley","nodeType":"place","placeType":"valley","scale":null,"degree":12,"size":3.5519594859692294,"x":-50.719146728515625,"y":-71.12852478027344,"community":11,"communityLabel":"San Luis Valley, Canon City, Lontra canadensis"},{"id":"place-7723","label":"Duck Creek","nodeType":"place","placeType":"stream","scale":null,"degree":24,"size":4.075100659894561,"x":-21.016719818115234,"y":-85.10906219482422,"community":11,"communityLabel":"San Luis Valley, Canon City, Lontra canadensis"},{"id":"place-7860","label":"Monarch Pass","nodeType":"place","placeType":"peak","scale":null,"degree":163,"size":5.579893142259359,"x":-39.8211784362793,"y":-8.097743034362793,"community":11,"communityLabel":"San Luis Valley, Canon City, Lontra canadensis"},{"id":"place-7853","label":"Gunnison Field Office","nodeType":"place","placeType":"office","scale":null,"degree":4,"size":2.7875503299472806,"x":85.09850311279297,"y":-45.51596450805664,"community":11,"communityLabel":"San Luis Valley, Canon City, Lontra canadensis"},{"id":"place-7855","label":"Sapinero","nodeType":"place","placeType":"town","scale":null,"degree":59,"size":4.775475649777681,"x":13.110770225524902,"y":-202.05783081054688,"community":11,"communityLabel":"San Luis Valley, Canon City, Lontra canadensis"},{"id":"place-7863","label":"Doyleville","nodeType":"place","placeType":"town","scale":null,"degree":68,"size":4.887285203677807,"x":-82.56602478027344,"y":0.5400354266166687,"community":11,"communityLabel":"San Luis Valley, Canon City, Lontra canadensis"},{"id":"place-7975","label":"Ute creek","nodeType":"place","placeType":"stream","scale":null,"degree":16,"size":3.766570675244973,"x":-98.7176513671875,"y":42.77139663696289,"community":11,"communityLabel":"San Luis Valley, Canon City, Lontra canadensis"},{"id":"place-8890","label":"Burlington","nodeType":"place","placeType":"town","scale":null,"degree":29,"size":4.220957905329724,"x":2.307508707046509,"y":87.72879028320312,"community":11,"communityLabel":"San Luis Valley, Canon City, Lontra canadensis"},{"id":"place-8958","label":"Georgetown","nodeType":"place","placeType":"town","scale":null,"degree":51,"size":4.660994974865142,"x":-10.826229095458984,"y":60.30034255981445,"community":11,"communityLabel":"San Luis Valley, Canon City, Lontra canadensis"},{"id":"place-8959","label":"Fruita","nodeType":"place","placeType":"town","scale":null,"degree":172,"size":5.622633275598224,"x":-53.71220397949219,"y":-25.18834114074707,"community":11,"communityLabel":"San Luis Valley, Canon City, Lontra canadensis"},{"id":"place-9073","label":"Bear Lake","nodeType":"place","placeType":"lake","scale":null,"degree":13,"size":3.6112458636922073,"x":-18.021230697631836,"y":93.80432891845703,"community":11,"communityLabel":"San Luis Valley, Canon City, Lontra canadensis"},{"id":"place-9133","label":"Delores River","nodeType":"place","placeType":"river","scale":null,"degree":12,"size":3.5519594859692294,"x":-9.307494163513184,"y":93.94157409667969,"community":11,"communityLabel":"San Luis Valley, Canon City, Lontra canadensis"},{"id":"place-9105","label":"Great Salt Lake","nodeType":"place","placeType":"lake","scale":null,"degree":19,"size":3.8965858188431928,"x":1.6558582782745361,"y":79.58718872070312,"community":11,"communityLabel":"San Luis Valley, Canon City, Lontra canadensis"},{"id":"place-9106","label":"Provo River","nodeType":"place","placeType":"stream","scale":null,"degree":10,"size":3.4183162182386964,"x":-39.52964401245117,"y":115.97462463378906,"community":11,"communityLabel":"San Luis Valley, Canon City, Lontra canadensis"},{"id":"place-12427","label":"Mesa de Maya Ranch","nodeType":"place","placeType":"ranch","scale":null,"degree":13,"size":3.6112458636922073,"x":-96.99397277832031,"y":34.994842529296875,"community":11,"communityLabel":"San Luis Valley, Canon City, Lontra canadensis"},{"id":"place-6749","label":"Conejos River","nodeType":"place","placeType":"river","scale":null,"degree":30,"size":4.247189763588118,"x":-93.8746109008789,"y":-19.20208168029785,"community":11,"communityLabel":"San Luis Valley, Canon City, Lontra canadensis"},{"id":"place-7119","label":"Canon City","nodeType":"place","placeType":"town","scale":null,"degree":394,"size":6.283108611920897,"x":51.47908401489258,"y":-14.790471076965332,"community":11,"communityLabel":"San Luis Valley, Canon City, Lontra canadensis"},{"id":"place-7715","label":"Royal Gorge","nodeType":"place","placeType":"valley","scale":null,"degree":54,"size":4.705866548185977,"x":50.28464889526367,"y":-27.412961959838867,"community":11,"communityLabel":"San Luis Valley, Canon City, Lontra canadensis"},{"id":"place-8792","label":"La Jara","nodeType":"place","placeType":"town","scale":null,"degree":8,"size":3.257779661868976,"x":-57.6488037109375,"y":104.96302795410156,"community":11,"communityLabel":"San Luis Valley, Canon City, Lontra canadensis"},{"id":"place-9083","label":"Black Hawk","nodeType":"place","placeType":"town","scale":null,"degree":48,"size":4.613456238488501,"x":-109.23048400878906,"y":49.106407165527344,"community":11,"communityLabel":"San Luis Valley, Canon City, Lontra canadensis"},{"id":"place-9084","label":"Empire","nodeType":"place","placeType":"town","scale":null,"degree":24,"size":4.075100659894561,"x":38.9046516418457,"y":44.81281280517578,"community":11,"communityLabel":"San Luis Valley, Canon City, Lontra canadensis"},{"id":"place-9085","label":"Silver Plume","nodeType":"place","placeType":"town","scale":null,"degree":32,"size":4.297206049173184,"x":-66.22884368896484,"y":75.16175842285156,"community":11,"communityLabel":"San Luis Valley, Canon City, Lontra canadensis"},{"id":"place-9297","label":"Fort Carson Military Reservation","nodeType":"place","placeType":"blm_land","scale":null,"degree":9,"size":3.342068074395237,"x":36.98845672607422,"y":33.02049255371094,"community":11,"communityLabel":"San Luis Valley, Canon City, Lontra canadensis"},{"id":"place-6568","label":"Ophir","nodeType":"place","placeType":"town","scale":null,"degree":36,"size":4.38873433011538,"x":32.2762336730957,"y":82.55372619628906,"community":11,"communityLabel":"San Luis Valley, Canon City, Lontra canadensis"},{"id":"place-6750","label":"Closed Basin","nodeType":"place","placeType":"watershed","scale":null,"degree":47,"size":4.596960808726313,"x":-86.90361785888672,"y":-18.325761795043945,"community":11,"communityLabel":"San Luis Valley, Canon City, Lontra canadensis"},{"id":"place-6751","label":"Monte Vista","nodeType":"place","placeType":"town","scale":null,"degree":79,"size":5.005621307739105,"x":-29.567548751831055,"y":-24.655752182006836,"community":11,"communityLabel":"San Luis Valley, Canon City, Lontra canadensis"},{"id":"place-7782","label":"South Fork","nodeType":"place","placeType":"town","scale":null,"degree":55,"size":4.72028135258812,"x":-90.0129623413086,"y":27.9858455657959,"community":11,"communityLabel":"San Luis Valley, Canon City, Lontra canadensis"},{"id":"place-8587","label":"Carbon County","nodeType":"place","placeType":"county","scale":null,"degree":24,"size":4.075100659894561,"x":-114.11022186279297,"y":-7.152622699737549,"community":11,"communityLabel":"San Luis Valley, Canon City, Lontra canadensis"},{"id":"place-8590","label":"Price","nodeType":"place","placeType":"town","scale":null,"degree":10,"size":3.4183162182386964,"x":-127.58988189697266,"y":2.693432569503784,"community":11,"communityLabel":"San Luis Valley, Canon City, Lontra canadensis"},{"id":"place-8708","label":"Blanca","nodeType":"place","placeType":"town","scale":null,"degree":4,"size":2.7875503299472806,"x":-116.33550262451172,"y":-80.39876556396484,"community":11,"communityLabel":"San Luis Valley, Canon City, Lontra canadensis"},{"id":"place-9140","label":"Richfield","nodeType":"place","placeType":"town","scale":null,"degree":13,"size":3.6112458636922073,"x":-57.04931640625,"y":113.54915618896484,"community":11,"communityLabel":"San Luis Valley, Canon City, Lontra canadensis"},{"id":"place-9873","label":"Middle Creek","nodeType":"place","placeType":"stream","scale":null,"degree":3,"size":2.6090354888959126,"x":-72.521484375,"y":102.13001251220703,"community":11,"communityLabel":"San Luis Valley, Canon City, Lontra canadensis"},{"id":"place-10079","label":"valley","nodeType":"place","placeType":"valley","scale":null,"degree":10,"size":3.4183162182386964,"x":-28.1637020111084,"y":89.25919342041016,"community":11,"communityLabel":"San Luis Valley, Canon City, Lontra canadensis"},{"id":"place-10508","label":"Bailey","nodeType":"place","placeType":"town","scale":null,"degree":20,"size":3.9356179501787385,"x":-105.19141387939453,"y":20.216190338134766,"community":11,"communityLabel":"San Luis Valley, Canon City, Lontra canadensis"},{"id":"place-10521","label":"Turkey Creek","nodeType":"place","placeType":"stream","scale":null,"degree":34,"size":4.344278449191531,"x":-86.87722778320312,"y":16.864892959594727,"community":11,"communityLabel":"San Luis Valley, Canon City, Lontra canadensis"},{"id":"place-11148","label":"West Valley","nodeType":"place","placeType":"town","scale":null,"degree":25,"size":4.106477230417186,"x":45.172447204589844,"y":40.779911041259766,"community":11,"communityLabel":"San Luis Valley, Canon City, Lontra canadensis"},{"id":"place-11369","label":"Clifton","nodeType":"place","placeType":"town","scale":null,"degree":34,"size":4.344278449191531,"x":-105.27406311035156,"y":-23.93264389038086,"community":11,"communityLabel":"San Luis Valley, Canon City, Lontra canadensis"},{"id":"place-11720","label":"Nathrop","nodeType":"place","placeType":"town","scale":null,"degree":24,"size":4.075100659894561,"x":-83.12425994873047,"y":9.09533977508545,"community":11,"communityLabel":"San Luis Valley, Canon City, Lontra canadensis"},{"id":"place-11794","label":"Sanford","nodeType":"place","placeType":"town","scale":null,"degree":7,"size":3.163553233343869,"x":-59.08576583862305,"y":81.2780532836914,"community":11,"communityLabel":"San Luis Valley, Canon City, Lontra canadensis"},{"id":"stakeholder-120","label":"Rio Grande Water Conservation District","nodeType":"stakeholder","stakeholderType":"other","degree":16,"size":3.766570675244973,"x":-13.622642517089844,"y":80.33983612060547,"community":11,"communityLabel":"San Luis Valley, Canon City, Lontra canadensis"},{"id":"stakeholder-391","label":"Wyoming Department of Transportation","nodeType":"stakeholder","stakeholderType":"other","degree":4,"size":2.7875503299472806,"x":3.35947847366333,"y":87.95194244384766,"community":11,"communityLabel":"San Luis Valley, Canon City, Lontra canadensis"},{"id":"stakeholder-453","label":"Citizens for San Luis Valley Water","nodeType":"stakeholder","stakeholderType":"other","degree":4,"size":2.7875503299472806,"x":-75.05133819580078,"y":58.40953826904297,"community":11,"communityLabel":"San Luis Valley, Canon City, Lontra canadensis"},{"id":"stakeholder-535","label":"Utah Department of Environmental Quality","nodeType":"stakeholder","stakeholderType":"other","degree":4,"size":2.7875503299472806,"x":-25.40679168701172,"y":18.4100284576416,"community":11,"communityLabel":"San Luis Valley, Canon City, Lontra canadensis"},{"id":"stakeholder-536","label":"University of Montana","nodeType":"stakeholder","stakeholderType":"academic","degree":4,"size":2.7875503299472806,"x":-29.231775283813477,"y":96.8229751586914,"community":11,"communityLabel":"San Luis Valley, Canon City, Lontra canadensis"},{"id":"stakeholder-628","label":"Conejos County Soil Conservation District","nodeType":"stakeholder","stakeholderType":"local_gov","degree":3,"size":2.6090354888959126,"x":1.7686938047409058,"y":88.09126281738281,"community":11,"communityLabel":"San Luis Valley, Canon City, Lontra canadensis"},{"id":"stakeholder-649","label":"CDOH","nodeType":"stakeholder","stakeholderType":"other","degree":3,"size":2.6090354888959126,"x":-70.79277038574219,"y":-1.5890164375305176,"community":11,"communityLabel":"San Luis Valley, Canon City, Lontra canadensis"},{"id":"stakeholder-659","label":"Utah Department of Natural Resources","nodeType":"stakeholder","stakeholderType":"other","degree":3,"size":2.6090354888959126,"x":-29.37187957763672,"y":94.22311401367188,"community":11,"communityLabel":"San Luis Valley, Canon City, Lontra canadensis"},{"id":"stakeholder-745","label":"U.S. Army","nodeType":"stakeholder","stakeholderType":"federal_agency","degree":3,"size":2.6090354888959126,"x":-65.32738494873047,"y":15.182011604309082,"community":11,"communityLabel":"San Luis Valley, Canon City, Lontra canadensis"},{"id":"stakeholder-747","label":"Idaho Fish and Game Department","nodeType":"stakeholder","stakeholderType":"other","degree":3,"size":2.6090354888959126,"x":-8.712777137756348,"y":80.0588607788086,"community":11,"communityLabel":"San Luis Valley, Canon City, Lontra canadensis"},{"id":"stakeholder-941","label":"Colorado Open Lands","nodeType":"stakeholder","stakeholderType":"state_agency","degree":2,"size":2.3788898309344875,"x":-95.82475280761719,"y":-55.319068908691406,"community":11,"communityLabel":"San Luis Valley, Canon City, Lontra canadensis"},{"id":"stakeholder-945","label":"Alamosa-LaJarn Water Conservancy District","nodeType":"stakeholder","stakeholderType":"local_gov","degree":2,"size":2.3788898309344875,"x":-12.858345031738281,"y":101.12750244140625,"community":11,"communityLabel":"San Luis Valley, Canon City, Lontra canadensis"},{"id":"stakeholder-1032","label":"Rio Grande National Forest","nodeType":"stakeholder","stakeholderType":"other","degree":2,"size":2.3788898309344875,"x":-56.5291748046875,"y":95.7613296508789,"community":11,"communityLabel":"San Luis Valley, Canon City, Lontra canadensis"},{"id":"stakeholder-1151","label":"Utah Division of Wildlife Resources","nodeType":"stakeholder","stakeholderType":"other","degree":2,"size":2.3788898309344875,"x":-6.181069850921631,"y":109.89615631103516,"community":11,"communityLabel":"San Luis Valley, Canon City, Lontra canadensis"},{"id":"stakeholder-1154","label":"Colorado School of Mines Research Institute","nodeType":"stakeholder","stakeholderType":"state_agency","degree":2,"size":2.3788898309344875,"x":-0.1278989017009735,"y":94.12924194335938,"community":11,"communityLabel":"San Luis Valley, Canon City, Lontra canadensis"},{"id":"stakeholder-1155","label":"USGS Water Resources Division","nodeType":"stakeholder","stakeholderType":"federal_agency","degree":2,"size":2.3788898309344875,"x":-33.08059310913086,"y":92.76831817626953,"community":11,"communityLabel":"San Luis Valley, Canon City, Lontra canadensis"},{"id":"stakeholder-1435","label":"Recreational Equipment Inc.","nodeType":"stakeholder","stakeholderType":"industry","degree":2,"size":2.3788898309344875,"x":-105.36669921875,"y":2.6715896129608154,"community":11,"communityLabel":"San Luis Valley, Canon City, Lontra canadensis"},{"id":"author-25585","label":"Daniel T. Blumstein","nodeType":"author","degree":723,"size":6.767833113908573,"x":95.61670684814453,"y":-10.931859016418457,"community":0,"communityLabel":"Marmota flaviventris, mark-recapture (Sciuridae), antipredator behavior"},{"id":"author-25716","label":"Conner S. Philson","nodeType":"author","degree":52,"size":4.676233530841698,"x":30.318519592285156,"y":29.347808837890625,"community":0,"communityLabel":"Marmota flaviventris, mark-recapture (Sciuridae), antipredator behavior"},{"id":"author-26312","label":"Colorado Department","nodeType":"author","degree":6,"size":3.0567281192442506,"x":-75.31094360351562,"y":-62.925418853759766,"community":11,"communityLabel":"San Luis Valley, Canon City, Lontra canadensis"},{"id":"author-26543","label":"Wynn R. Walker","nodeType":"author","degree":4,"size":2.7875503299472806,"x":-32.322872161865234,"y":-122.43680572509766,"community":11,"communityLabel":"San Luis Valley, Canon City, Lontra canadensis"},{"id":"author-26787","label":"R. E. Denison","nodeType":"author","degree":2,"size":2.3788898309344875,"x":85.56781005859375,"y":-72.80442810058594,"community":11,"communityLabel":"San Luis Valley, Canon City, Lontra canadensis"},{"id":"author-27399","label":"Gaylord V. Skogerboe","nodeType":"author","degree":3,"size":2.6090354888959126,"x":-36.97395324707031,"y":-123.55571746826172,"community":11,"communityLabel":"San Luis Valley, Canon City, Lontra canadensis"},{"id":"author-26848","label":"R. Evans","nodeType":"author","degree":2,"size":2.3788898309344875,"x":27.785442352294922,"y":-123.11587524414062,"community":11,"communityLabel":"San Luis Valley, Canon City, Lontra canadensis"},{"id":"pub-1343","label":"Acoustic monitoring in terrestrial environments us","nodeType":"publication","degree":31,"size":4.272588722239782,"x":147.7326202392578,"y":30.67095947265625,"community":87,"communityLabel":"not specified, camera trapping, ENSBox collaborative acoustic localization"},{"id":"pub-1682","label":"Developing an evolutionary ecology of fear: how li","nodeType":"publication","degree":45,"size":4.562913117191276,"x":55.51997375488281,"y":3.624696969985962,"community":2,"communityLabel":"Woodpecker, Selasphorus platycercus, habitat fragmentation"},{"id":"pub-1357","label":"Quantifying human disturbance on antipredator beha","nodeType":"publication","degree":58,"size":4.762029955124576,"x":57.40944290161133,"y":63.76310348510742,"community":0,"communityLabel":"Marmota flaviventris, mark-recapture (Sciuridae), antipredator behavior"},{"id":"pub-4066","label":"A brief review of the geology of the San Juan regi","nodeType":"publication","degree":129,"size":5.394027560364465,"x":-92.75743865966797,"y":29.664907455444336,"community":64,"communityLabel":"surface runoff, avalanche dynamics modeling, Bear Creek"},{"id":"pub-1517","label":"A trait-based approach to the evolution of complex","nodeType":"publication","degree":22,"size":4.00839537274332,"x":93.92643737792969,"y":53.04646682739258,"community":0,"communityLabel":"Marmota flaviventris, mark-recapture (Sciuridae), antipredator behavior"},{"id":"pub-3985","label":"Middle Jurassic Todilto Formation of northern New ","nodeType":"publication","degree":26,"size":4.136669492803463,"x":64.07929229736328,"y":-91.15805053710938,"community":11,"communityLabel":"San Luis Valley, Canon City, Lontra canadensis"},{"id":"pub-4044","label":"Late Devonian fresh-water fishes from the western ","nodeType":"publication","degree":2,"size":2.3788898309344875,"x":83.67473602294922,"y":-68.16460418701172,"community":11,"communityLabel":"San Luis Valley, Canon City, Lontra canadensis"},{"id":"pub-211","label":"Emergent social structure is typically not associa","nodeType":"publication","degree":62,"size":4.814507781113226,"x":70.01660919189453,"y":59.22504425048828,"community":0,"communityLabel":"Marmota flaviventris, mark-recapture (Sciuridae), antipredator behavior"},{"id":"pub-4913","label":"Salt Pickup from Agricultural Lands in the Grand V","nodeType":"publication","degree":2,"size":2.3788898309344875,"x":-67.29410552978516,"y":-111.35978698730469,"community":11,"communityLabel":"San Luis Valley, Canon City, Lontra canadensis"},{"id":"pub-4916","label":"Developing best management practices for salinity ","nodeType":"publication","degree":3,"size":2.6090354888959126,"x":0.8049567937850952,"y":-151.23483276367188,"community":11,"communityLabel":"San Luis Valley, Canon City, Lontra canadensis"},{"id":"pub-4751","label":"Changes in hunting season regulations (1870s–2019)","nodeType":"publication","degree":44,"size":4.545329991816256,"x":44.93517303466797,"y":44.73963928222656,"community":59,"communityLabel":"Sage grouse, Centrocercus urophasianus, fire disturbance"},{"id":"pub-657","label":"Social transmission of a novel foraging trait in y","nodeType":"publication","degree":22,"size":4.00839537274332,"x":50.432193756103516,"y":68.90371704101562,"community":0,"communityLabel":"Marmota flaviventris, mark-recapture (Sciuridae), antipredator behavior"},{"id":"pub-1420","label":"Late Quaternary Paleoecology of Two High-Elevation","nodeType":"publication","degree":119,"size":5.329993394225637,"x":-42.35569381713867,"y":46.74403762817383,"community":9,"communityLabel":"phenology, upper East River Valley, Juniperus"},{"id":"pub-838","label":"A cost of being amicable in a hibernating marmot.","nodeType":"publication","degree":44,"size":4.545329991816256,"x":92.07170867919922,"y":29.688871383666992,"community":0,"communityLabel":"Marmota flaviventris, mark-recapture (Sciuridae), antipredator behavior"},{"id":"pub-51","label":"Out of sight, out of mind: The role of carcass bur","nodeType":"publication","degree":15,"size":3.718070977791825,"x":102.84918975830078,"y":69.40528869628906,"community":33,"communityLabel":"small mammals, Peromyscus, maternal care"},{"id":"pub-314","label":"Marmot mass gain rates relate to their group’s soc","nodeType":"publication","degree":56,"size":4.73444101426764,"x":74.33950805664062,"y":34.36589050292969,"community":0,"communityLabel":"Marmota flaviventris, mark-recapture (Sciuridae), antipredator behavior"},{"id":"document-2788","label":"25 Facts About Water in the San Luis Valley","nodeType":"document","documentType":"technical_report","degree":22,"size":4.00839537274332,"x":-83.32713317871094,"y":-47.75955581665039,"community":11,"communityLabel":"San Luis Valley, Canon City, Lontra canadensis"},{"id":"document-2841","label":"Agricultural Land Conversion in Colorado A Prelimi","nodeType":"document","documentType":"technical_report","degree":41,"size":4.490135694626694,"x":-80.90676879882812,"y":-60.37255096435547,"community":11,"communityLabel":"San Luis Valley, Canon City, Lontra canadensis"},{"id":"document-2876","label":"Appendix 2 List of Designated Colorado Natural Are","nodeType":"document","documentType":"environmental_assessment","degree":379,"size":6.252137002176346,"x":-61.7411003112793,"y":-77.07295989990234,"community":11,"communityLabel":"San Luis Valley, Canon City, Lontra canadensis"},{"id":"document-3061","label":"Colorado's Wildlife Company: Habitat Crisis","nodeType":"document","documentType":"news_article","degree":102,"size":5.207783190583709,"x":35.621376037597656,"y":46.92109680175781,"community":11,"communityLabel":"San Luis Valley, Canon City, Lontra canadensis"},{"id":"document-3080","label":"Community- Based Environmental Protection FY 1996 ","nodeType":"document","documentType":"technical_report","degree":256,"size":5.939260867916176,"x":15.311145782470703,"y":109.69188690185547,"community":11,"communityLabel":"San Luis Valley, Canon City, Lontra canadensis"},{"id":"document-3102","label":"Corridor 87-277 Section 368 Energy Corridor Region","nodeType":"document","documentType":"environmental_assessment","degree":131,"size":5.4062415380690965,"x":63.12407302856445,"y":-32.504005432128906,"community":11,"communityLabel":"San Luis Valley, Canon City, Lontra canadensis"},{"id":"document-3183","label":"Engineer sounds valley aquifer alarm","nodeType":"document","documentType":"news_article","degree":11,"size":3.4879253198304,"x":-70.37506866455078,"y":-10.564266204833984,"community":11,"communityLabel":"San Luis Valley, Canon City, Lontra canadensis"},{"id":"document-3232","label":"Field Excursion to Colorado and Utah, Western Unit","nodeType":"document","documentType":"technical_report","degree":227,"size":5.843476503163553,"x":-106.94078063964844,"y":42.39472961425781,"community":11,"communityLabel":"San Luis Valley, Canon City, Lontra canadensis"},{"id":"document-3428","label":"Late Night Planning Reader – Housing","nodeType":"document","documentType":null,"degree":11,"size":3.4879253198304,"x":105.75965881347656,"y":25.083511352539062,"community":11,"communityLabel":"San Luis Valley, Canon City, Lontra canadensis"},{"id":"document-3552","label":"Negotiations Continue on Federal Water Rights","nodeType":"document","documentType":"news_article","degree":10,"size":3.4183162182386964,"x":-38.46531295776367,"y":88.25458526611328,"community":11,"communityLabel":"San Luis Valley, Canon City, Lontra canadensis"},{"id":"document-3807","label":"SLV Pastors Discuss Water Issues and Stewardship","nodeType":"document","documentType":"news_article","degree":7,"size":3.163553233343869,"x":-11.69853687286377,"y":88.82647705078125,"community":11,"communityLabel":"San Luis Valley, Canon City, Lontra canadensis"},{"id":"document-3952","label":"The Last Ranch: A Colorado Community and the Comin","nodeType":"document","documentType":"other","degree":10,"size":3.4183162182386964,"x":-33.01472854614258,"y":79.98140716552734,"community":11,"communityLabel":"San Luis Valley, Canon City, Lontra canadensis"},{"id":"document-3967","label":"The Rio Grande","nodeType":"document","documentType":"news_article","degree":48,"size":4.613456238488501,"x":-42.96919631958008,"y":3.693491220474243,"community":11,"communityLabel":"San Luis Valley, Canon City, Lontra canadensis"},{"id":"document-4100","label":"Well water dropping to critical levels","nodeType":"document","documentType":"news_article","degree":17,"size":3.8122974063169317,"x":-25.989904403686523,"y":109.49461364746094,"community":11,"communityLabel":"San Luis Valley, Canon City, Lontra canadensis"}],"edges":[{"source":"concept-9789","target":"place-6741","weight":1},{"source":"concept-10147","target":"place-6741","weight":1},{"source":"concept-10147","target":"place-7723","weight":1},{"source":"concept-10147","target":"species-9275","weight":1},{"source":"concept-10147","target":"species-10042","weight":1},{"source":"concept-10147","target":"species-10044","weight":1},{"source":"concept-10147","target":"species-10059","weight":1},{"source":"concept-10147","target":"species-10943","weight":1},{"source":"concept-10147","target":"species-10944","weight":1},{"source":"concept-10147","target":"species-10945","weight":1},{"source":"concept-10147","target":"species-10946","weight":1},{"source":"concept-10147","target":"species-10947","weight":1},{"source":"concept-10147","target":"species-10948","weight":1},{"source":"concept-10147","target":"species-10949","weight":1},{"source":"concept-10147","target":"species-10950","weight":1},{"source":"concept-10147","target":"species-10952","weight":1},{"source":"place-6568","target":"place-7119","weight":1},{"source":"place-6568","target":"place-9084","weight":1},{"source":"place-6741","target":"place-6744","weight":1.5},{"source":"place-6741","target":"place-6745","weight":2},{"source":"place-6741","target":"place-6749","weight":1.5},{"source":"place-6741","target":"place-6750","weight":2.5},{"source":"place-6741","target":"place-6751","weight":2.5},{"source":"place-6741","target":"place-7119","weight":2.5},{"source":"place-6741","target":"place-7355","weight":1.5},{"source":"place-6741","target":"place-7699","weight":1},{"source":"place-6741","target":"place-7707","weight":1},{"source":"place-6741","target":"place-7715","weight":1},{"source":"place-6741","target":"place-7723","weight":1},{"source":"place-6741","target":"place-7782","weight":1},{"source":"place-6741","target":"place-7860","weight":2},{"source":"place-6741","target":"place-7863","weight":1},{"source":"place-6741","target":"place-7975","weight":1},{"source":"place-6741","target":"place-8792","weight":1},{"source":"place-6741","target":"place-8890","weight":1},{"source":"place-6741","target":"place-8958","weight":2},{"source":"place-6741","target":"place-8959","weight":2.5},{"source":"place-6741","target":"place-9083","weight":1.5},{"source":"place-6741","target":"place-9085","weight":1},{"source":"place-6741","target":"place-9297","weight":1},{"source":"place-6741","target":"place-10079","weight":1},{"source":"place-6741","target":"place-10521","weight":1.5},{"source":"place-6741","target":"place-11720","weight":1},{"source":"place-6741","target":"place-11794","weight":1},{"source":"place-6741","target":"place-12427","weight":1},{"source":"place-6741","target":"species-8916","weight":1.5},{"source":"place-6741","target":"species-8963","weight":1.5},{"source":"place-6741","target":"species-8990","weight":2},{"source":"place-6741","target":"species-9088","weight":1.5},{"source":"place-6741","target":"species-9192","weight":1},{"source":"place-6741","target":"species-9196","weight":1},{"source":"place-6741","target":"species-9268","weight":1},{"source":"place-6741","target":"species-9275","weight":1},{"source":"place-6741","target":"species-9458","weight":1},{"source":"place-6741","target":"species-9462","weight":1},{"source":"place-6741","target":"species-9463","weight":2},{"source":"place-6741","target":"species-9521","weight":1},{"source":"place-6741","target":"species-9711","weight":2},{"source":"place-6741","target":"species-10042","weight":1},{"source":"place-6741","target":"species-10059","weight":1},{"source":"place-6741","target":"species-10943","weight":1.5},{"source":"place-6741","target":"species-10944","weight":1.5},{"source":"place-6741","target":"species-10945","weight":1.5},{"source":"place-6741","target":"species-10946","weight":1.5},{"source":"place-6741","target":"species-10947","weight":1.5},{"source":"place-6741","target":"species-10948","weight":1.5},{"source":"place-6741","target":"species-10949","weight":1.5},{"source":"place-6741","target":"species-10950","weight":1.5},{"source":"place-6741","target":"species-10952","weight":1},{"source":"place-6744","target":"place-6745","weight":1},{"source":"place-6744","target":"place-6749","weight":1},{"source":"place-6744","target":"place-6750","weight":1},{"source":"place-6744","target":"place-6751","weight":1},{"source":"place-6744","target":"place-7782","weight":1},{"source":"place-6745","target":"place-6749","weight":1},{"source":"place-6745","target":"place-6750","weight":1.5},{"source":"place-6745","target":"place-6751","weight":1},{"source":"place-6745","target":"place-8708","weight":1},{"source":"place-6749","target":"place-6750","weight":1},{"source":"place-6750","target":"place-6751","weight":1.5},{"source":"place-6751","target":"place-8959","weight":1},{"source":"place-7119","target":"place-7355","weight":1},{"source":"place-7119","target":"place-7715","weight":2},{"source":"place-7119","target":"place-7860","weight":1},{"source":"place-7119","target":"place-8958","weight":1},{"source":"place-7119","target":"place-9084","weight":1},{"source":"place-7119","target":"place-11148","weight":1},{"source":"place-7119","target":"species-8916","weight":1.5},{"source":"place-7119","target":"species-8963","weight":1},{"source":"place-7119","target":"species-8990","weight":1.5},{"source":"place-7119","target":"species-9088","weight":1.5},{"source":"place-7119","target":"species-9275","weight":1},{"source":"place-7119","target":"species-9463","weight":1},{"source":"place-7119","target":"species-9711","weight":1.5},{"source":"place-7119","target":"species-10943","weight":1},{"source":"place-7119","target":"species-10944","weight":1},{"source":"place-7119","target":"species-10945","weight":1},{"source":"place-7119","target":"species-10946","weight":1},{"source":"place-7119","target":"species-10947","weight":1},{"source":"place-7119","target":"species-10948","weight":1},{"source":"place-7119","target":"species-10949","weight":1},{"source":"place-7119","target":"species-10950","weight":1},{"source":"place-7355","target":"place-8958","weight":1},{"source":"place-7355","target":"place-9083","weight":1},{"source":"place-7355","target":"place-9085","weight":1},{"source":"place-7355","target":"place-10521","weight":1},{"source":"place-7699","target":"species-9192","weight":1},{"source":"place-7699","target":"species-9196","weight":1},{"source":"place-7707","target":"species-8963","weight":1},{"source":"place-7707","target":"species-8990","weight":1},{"source":"place-7707","target":"species-9463","weight":1},{"source":"place-7707","target":"species-9711","weight":1},{"source":"place-7707","target":"species-10059","weight":1},{"source":"place-7715","target":"species-8990","weight":1},{"source":"place-7715","target":"species-9275","weight":1},{"source":"place-7715","target":"species-9711","weight":1},{"source":"place-7715","target":"species-10943","weight":1},{"source":"place-7715","target":"species-10944","weight":1},{"source":"place-7715","target":"species-10945","weight":1},{"source":"place-7715","target":"species-10946","weight":1},{"source":"place-7715","target":"species-10947","weight":1},{"source":"place-7715","target":"species-10948","weight":1},{"source":"place-7715","target":"species-10949","weight":1},{"source":"place-7715","target":"species-10950","weight":1},{"source":"place-7723","target":"species-10943","weight":1},{"source":"place-7723","target":"species-10944","weight":1},{"source":"place-7723","target":"species-10945","weight":1},{"source":"place-7723","target":"species-10946","weight":1},{"source":"place-7723","target":"species-10947","weight":1},{"source":"place-7723","target":"species-10948","weight":1},{"source":"place-7723","target":"species-10949","weight":1},{"source":"place-7723","target":"species-10950","weight":1},{"source":"place-7723","target":"species-10952","weight":1},{"source":"place-7855","target":"place-7860","weight":1},{"source":"place-7855","target":"place-7863","weight":2},{"source":"place-7860","target":"place-7863","weight":1},{"source":"place-7860","target":"species-10943","weight":1},{"source":"place-7860","target":"species-10944","weight":1},{"source":"place-7860","target":"species-10945","weight":1},{"source":"place-7860","target":"species-10946","weight":1},{"source":"place-7860","target":"species-10947","weight":1},{"source":"place-7860","target":"species-10948","weight":1},{"source":"place-7860","target":"species-10949","weight":1},{"source":"place-7860","target":"species-10950","weight":1},{"source":"place-8587","target":"place-8590","weight":1},{"source":"place-8792","target":"place-10079","weight":1},{"source":"place-8792","target":"place-11794","weight":1},{"source":"place-8958","target":"place-8959","weight":1},{"source":"place-8958","target":"place-9083","weight":1},{"source":"place-8958","target":"place-9085","weight":1},{"source":"place-8958","target":"species-8916","weight":1},{"source":"place-8958","target":"species-8963","weight":1},{"source":"place-8958","target":"species-8990","weight":1},{"source":"place-8958","target":"species-9088","weight":1},{"source":"place-8958","target":"species-9463","weight":1},{"source":"place-8958","target":"species-9711","weight":1},{"source":"place-8959","target":"place-9083","weight":1},{"source":"place-8959","target":"place-11369","weight":1},{"source":"place-8959","target":"place-11720","weight":1},{"source":"place-8959","target":"species-9458","weight":1.5},{"source":"place-8959","target":"species-9470","weight":1},{"source":"place-9073","target":"place-9140","weight":1},{"source":"place-9083","target":"place-9085","weight":1},{"source":"place-10079","target":"place-11794","weight":1},{"source":"place-11148","target":"species-8916","weight":1},{"source":"place-11148","target":"species-9088","weight":1},{"source":"species-8916","target":"species-8963","weight":1},{"source":"species-8916","target":"species-8990","weight":1},{"source":"species-8916","target":"species-9075","weight":1},{"source":"species-8916","target":"species-9088","weight":2.5},{"source":"species-8916","target":"species-9462","weight":1},{"source":"species-8916","target":"species-9463","weight":1},{"source":"species-8916","target":"species-9711","weight":1},{"source":"species-8963","target":"species-8990","weight":1.5},{"source":"species-8963","target":"species-8996","weight":1},{"source":"species-8963","target":"species-9088","weight":1},{"source":"species-8963","target":"species-9462","weight":1},{"source":"species-8963","target":"species-9463","weight":2.5},{"source":"species-8963","target":"species-9711","weight":1.5},{"source":"species-8963","target":"species-10059","weight":1},{"source":"species-8990","target":"species-9088","weight":1},{"source":"species-8990","target":"species-9275","weight":1},{"source":"species-8990","target":"species-9463","weight":1.5},{"source":"species-8990","target":"species-9711","weight":2.5},{"source":"species-8990","target":"species-10059","weight":1},{"source":"species-8990","target":"species-10943","weight":1},{"source":"species-8990","target":"species-10944","weight":1},{"source":"species-8990","target":"species-10945","weight":1},{"source":"species-8990","target":"species-10946","weight":1},{"source":"species-8990","target":"species-10947","weight":1},{"source":"species-8990","target":"species-10948","weight":1},{"source":"species-8990","target":"species-10949","weight":1},{"source":"species-8990","target":"species-10950","weight":1},{"source":"species-8996","target":"species-9463","weight":1},{"source":"species-9075","target":"species-9088","weight":1},{"source":"species-9088","target":"species-9462","weight":1},{"source":"species-9088","target":"species-9463","weight":1},{"source":"species-9088","target":"species-9711","weight":1},{"source":"species-9192","target":"species-9196","weight":1},{"source":"species-9275","target":"species-9711","weight":1},{"source":"species-9275","target":"species-10943","weight":1},{"source":"species-9275","target":"species-10944","weight":1},{"source":"species-9275","target":"species-10945","weight":1},{"source":"species-9275","target":"species-10946","weight":1},{"source":"species-9275","target":"species-10947","weight":1},{"source":"species-9275","target":"species-10948","weight":1},{"source":"species-9275","target":"species-10949","weight":1},{"source":"species-9275","target":"species-10950","weight":1},{"source":"species-9458","target":"species-9470","weight":1},{"source":"species-9462","target":"species-9463","weight":1.5},{"source":"species-9463","target":"species-9711","weight":1.5},{"source":"species-9463","target":"species-10059","weight":1},{"source":"species-9521","target":"species-10042","weight":1.5},{"source":"species-9711","target":"species-9712","weight":1},{"source":"species-9711","target":"species-9903","weight":1.5},{"source":"species-9711","target":"species-10059","weight":1},{"source":"species-9711","target":"species-10943","weight":1},{"source":"species-9711","target":"species-10944","weight":1},{"source":"species-9711","target":"species-10945","weight":1},{"source":"species-9711","target":"species-10946","weight":1},{"source":"species-9711","target":"species-10947","weight":1},{"source":"species-9711","target":"species-10948","weight":1},{"source":"species-9711","target":"species-10949","weight":1},{"source":"species-9711","target":"species-10950","weight":1},{"source":"species-10042","target":"species-10044","weight":1},{"source":"species-10042","target":"species-10059","weight":1},{"source":"species-10044","target":"species-10059","weight":1},{"source":"species-10943","target":"species-10944","weight":2},{"source":"species-10943","target":"species-10945","weight":2},{"source":"species-10943","target":"species-10946","weight":2},{"source":"species-10943","target":"species-10947","weight":2},{"source":"species-10943","target":"species-10948","weight":2},{"source":"species-10943","target":"species-10949","weight":2},{"source":"species-10943","target":"species-10950","weight":2},{"source":"species-10943","target":"species-10952","weight":1},{"source":"species-10944","target":"species-10945","weight":2},{"source":"species-10944","target":"species-10946","weight":2},{"source":"species-10944","target":"species-10947","weight":2},{"source":"species-10944","target":"species-10948","weight":2},{"source":"species-10944","target":"species-10949","weight":2},{"source":"species-10944","target":"species-10950","weight":2},{"source":"species-10944","target":"species-10952","weight":1},{"source":"species-10945","target":"species-10946","weight":2},{"source":"species-10945","target":"species-10947","weight":2},{"source":"species-10945","target":"species-10948","weight":2},{"source":"species-10945","target":"species-10949","weight":2},{"source":"species-10945","target":"species-10950","weight":2},{"source":"species-10945","target":"species-10952","weight":1},{"source":"species-10946","target":"species-10947","weight":2},{"source":"species-10946","target":"species-10948","weight":2},{"source":"species-10946","target":"species-10949","weight":2},{"source":"species-10946","target":"species-10950","weight":2},{"source":"species-10946","target":"species-10952","weight":1},{"source":"species-10947","target":"species-10948","weight":2},{"source":"species-10947","target":"species-10949","weight":2},{"source":"species-10947","target":"species-10950","weight":2},{"source":"species-10947","target":"species-10952","weight":1},{"source":"species-10948","target":"species-10949","weight":2},{"source":"species-10948","target":"species-10950","weight":2},{"source":"species-10948","target":"species-10952","weight":1},{"source":"species-10949","target":"species-10950","weight":2},{"source":"species-10949","target":"species-10952","weight":1},{"source":"species-10950","target":"species-10952","weight":1},{"source":"species-9458","target":"pub-1420","weight":2},{"source":"species-9088","target":"pub-211","weight":2},{"source":"species-9088","target":"pub-314","weight":2},{"source":"species-9088","target":"pub-657","weight":2},{"source":"species-9088","target":"pub-1517","weight":2},{"source":"species-9088","target":"pub-838","weight":2},{"source":"concept-8641","target":"pub-3985","weight":2},{"source":"concept-10147","target":"pub-1420","weight":2},{"source":"place-6741","target":"pub-4066","weight":2},{"source":"place-6744","target":"pub-4066","weight":2},{"source":"place-6749","target":"pub-4066","weight":2},{"source":"place-7782","target":"pub-4066","weight":2},{"source":"place-7975","target":"pub-4066","weight":2},{"source":"species-8963","target":"pub-4751","weight":2},{"source":"species-8990","target":"pub-1357","weight":2},{"source":"species-8990","target":"pub-1343","weight":2},{"source":"species-9463","target":"pub-4751","weight":2},{"source":"species-8916","target":"pub-211","weight":2},{"source":"species-8916","target":"pub-314","weight":2},{"source":"species-8916","target":"pub-657","weight":2},{"source":"species-8916","target":"pub-1517","weight":2},{"source":"species-8916","target":"pub-838","weight":2},{"source":"species-8996","target":"pub-4751","weight":2},{"source":"species-9462","target":"pub-4751","weight":2},{"source":"species-9521","target":"pub-1682","weight":2},{"source":"species-9711","target":"pub-51","weight":2},{"source":"species-9711","target":"pub-1357","weight":2},{"source":"species-9711","target":"pub-1343","weight":2},{"source":"species-9903","target":"pub-51","weight":2},{"source":"species-10042","target":"pub-1682","weight":2},{"source":"species-10943","target":"pub-3985","weight":2},{"source":"species-10944","target":"pub-3985","weight":2},{"source":"species-10945","target":"pub-3985","weight":2},{"source":"species-10946","target":"pub-3985","weight":2},{"source":"species-10947","target":"pub-3985","weight":2},{"source":"species-10948","target":"pub-3985","weight":2},{"source":"species-10949","target":"pub-3985","weight":2},{"source":"species-10950","target":"pub-3985","weight":2},{"source":"author-25585","target":"pub-1682","weight":6},{"source":"author-25585","target":"pub-211","weight":6},{"source":"author-25585","target":"pub-314","weight":6},{"source":"author-25585","target":"pub-838","weight":6},{"source":"author-25585","target":"pub-1343","weight":6},{"source":"author-25585","target":"pub-1357","weight":6},{"source":"author-25585","target":"pub-1517","weight":6},{"source":"author-25716","target":"pub-211","weight":6},{"source":"author-25716","target":"pub-314","weight":6},{"source":"author-26543","target":"pub-4913","weight":6},{"source":"author-26543","target":"pub-4916","weight":6},{"source":"author-26787","target":"pub-4044","weight":6},{"source":"author-26787","target":"pub-3985","weight":6},{"source":"author-26848","target":"pub-4916","weight":6},{"source":"author-26848","target":"pub-3985","weight":6},{"source":"author-27399","target":"pub-4913","weight":6},{"source":"author-27399","target":"pub-4916","weight":6},{"source":"author-26543","target":"author-27399","weight":5},{"source":"author-25585","target":"author-25716","weight":35},{"source":"author-25585","target":"species-8916","weight":8},{"source":"author-25585","target":"species-8990","weight":4},{"source":"author-25585","target":"species-9088","weight":8},{"source":"author-25585","target":"species-9711","weight":4},{"source":"author-25716","target":"species-8916","weight":4},{"source":"author-25716","target":"species-9088","weight":4},{"source":"author-26312","target":"place-6745","weight":4},{"source":"document-2876","target":"species-8963","weight":2},{"source":"document-3061","target":"species-8963","weight":2},{"source":"document-3080","target":"species-8963","weight":2},{"source":"document-2876","target":"species-8990","weight":2},{"source":"document-3102","target":"species-8990","weight":2},{"source":"document-2876","target":"species-8996","weight":2},{"source":"document-3061","target":"species-9075","weight":2},{"source":"document-3061","target":"species-9088","weight":2},{"source":"document-3102","target":"species-9275","weight":2},{"source":"document-3061","target":"species-9458","weight":2},{"source":"document-3061","target":"species-9462","weight":2},{"source":"document-3061","target":"species-9463","weight":2},{"source":"document-3061","target":"species-9466","weight":2},{"source":"document-3061","target":"species-9470","weight":2},{"source":"document-3061","target":"species-8990","weight":2},{"source":"document-3061","target":"species-10059","weight":2},{"source":"document-3080","target":"species-9088","weight":2},{"source":"document-2788","target":"concept-9789","weight":2},{"source":"document-2876","target":"concept-10147","weight":2},{"source":"document-3232","target":"concept-10147","weight":2},{"source":"document-3080","target":"concept-10603","weight":2},{"source":"document-3102","target":"concept-10654","weight":2},{"source":"document-3232","target":"concept-11532","weight":2},{"source":"document-3232","target":"species-10943","weight":2},{"source":"document-3232","target":"species-10944","weight":2},{"source":"document-3232","target":"species-10945","weight":2},{"source":"document-3232","target":"species-10946","weight":2},{"source":"document-3232","target":"species-10947","weight":2},{"source":"document-3232","target":"species-10948","weight":2},{"source":"document-3232","target":"species-10949","weight":2},{"source":"document-3232","target":"species-10950","weight":2},{"source":"document-3232","target":"species-10952","weight":2},{"source":"document-3080","target":"place-6568","weight":2},{"source":"document-2788","target":"place-6741","weight":2},{"source":"document-2841","target":"place-6741","weight":2},{"source":"document-2876","target":"place-6741","weight":2},{"source":"document-3061","target":"place-6741","weight":2},{"source":"document-3080","target":"place-6741","weight":2},{"source":"document-3102","target":"place-6741","weight":2},{"source":"document-3552","target":"place-6741","weight":2},{"source":"document-3807","target":"place-6741","weight":2},{"source":"document-3952","target":"place-6741","weight":2},{"source":"document-3967","target":"place-6741","weight":2},{"source":"document-4100","target":"place-6741","weight":2},{"source":"document-3183","target":"place-6741","weight":2},{"source":"document-3232","target":"place-6741","weight":2},{"source":"document-2788","target":"place-6744","weight":2},{"source":"document-3967","target":"place-6744","weight":2},{"source":"document-2788","target":"place-6745","weight":2},{"source":"document-2841","target":"place-6745","weight":2},{"source":"document-3967","target":"place-6745","weight":2},{"source":"document-2788","target":"place-6749","weight":2},{"source":"document-2788","target":"place-6750","weight":2},{"source":"document-3967","target":"place-6750","weight":2},{"source":"document-3183","target":"place-6750","weight":2},{"source":"document-2788","target":"place-6751","weight":2},{"source":"document-3061","target":"place-6751","weight":2},{"source":"document-3967","target":"place-6751","weight":2},{"source":"document-3183","target":"place-6751","weight":2},{"source":"document-2876","target":"place-7119","weight":2},{"source":"document-3080","target":"place-7119","weight":2},{"source":"document-3102","target":"place-7119","weight":2},{"source":"document-2841","target":"place-7202","weight":2},{"source":"document-3080","target":"place-7355","weight":2},{"source":"document-3232","target":"place-7355","weight":2},{"source":"document-2876","target":"place-7699","weight":2},{"source":"document-2876","target":"place-7705","weight":2},{"source":"document-2876","target":"place-7707","weight":2},{"source":"document-3061","target":"place-7707","weight":2},{"source":"document-2876","target":"place-7715","weight":2},{"source":"document-3102","target":"place-7715","weight":2},{"source":"document-2876","target":"place-7721","weight":2},{"source":"document-2876","target":"place-7723","weight":2},{"source":"document-3232","target":"place-7723","weight":2},{"source":"document-3967","target":"place-7782","weight":2},{"source":"document-3102","target":"place-7853","weight":2},{"source":"document-3232","target":"place-7855","weight":2},{"source":"document-3102","target":"place-7860","weight":2},{"source":"document-3232","target":"place-7860","weight":2},{"source":"document-3232","target":"place-7863","weight":2},{"source":"document-4100","target":"place-7975","weight":2},{"source":"document-3232","target":"place-8587","weight":2},{"source":"document-3232","target":"place-8590","weight":2},{"source":"document-3967","target":"place-8708","weight":2},{"source":"document-3967","target":"place-8792","weight":2},{"source":"document-4100","target":"place-8792","weight":2},{"source":"document-3061","target":"place-8890","weight":2},{"source":"document-3061","target":"place-8958","weight":2},{"source":"document-3080","target":"place-8958","weight":2},{"source":"document-3232","target":"place-8958","weight":2},{"source":"document-3061","target":"place-8959","weight":2},{"source":"document-3232","target":"place-8959","weight":2},{"source":"document-3080","target":"place-9073","weight":2},{"source":"document-3080","target":"place-9083","weight":2},{"source":"document-3232","target":"place-9083","weight":2},{"source":"document-3080","target":"place-9084","weight":2},{"source":"document-3080","target":"place-9085","weight":2},{"source":"document-3232","target":"place-9085","weight":2},{"source":"document-3080","target":"place-9105","weight":2},{"source":"document-3080","target":"place-9106","weight":2},{"source":"document-3080","target":"place-9133","weight":2},{"source":"document-3080","target":"place-9140","weight":2},{"source":"document-3102","target":"place-9297","weight":2},{"source":"document-3552","target":"place-9873","weight":2},{"source":"document-3967","target":"place-10079","weight":2},{"source":"document-4100","target":"place-10079","weight":2},{"source":"document-3232","target":"place-10508","weight":2},{"source":"document-3232","target":"place-10521","weight":2},{"source":"document-3080","target":"place-11148","weight":2},{"source":"document-3232","target":"place-11369","weight":2},{"source":"document-3232","target":"place-11720","weight":2},{"source":"document-3967","target":"place-11794","weight":2},{"source":"document-4100","target":"place-11794","weight":2},{"source":"document-3232","target":"place-12427","weight":2},{"source":"document-2876","target":"species-9275","weight":2},{"source":"document-3080","target":"species-8990","weight":2},{"source":"document-2876","target":"species-9463","weight":2},{"source":"document-3080","target":"species-9463","weight":2},{"source":"document-3061","target":"species-8916","weight":2},{"source":"document-3080","target":"species-8916","weight":2},{"source":"document-2876","target":"species-9192","weight":2},{"source":"document-2876","target":"species-9196","weight":2},{"source":"document-2876","target":"species-9268","weight":2},{"source":"document-2876","target":"species-9521","weight":2},{"source":"document-2876","target":"species-9711","weight":2},{"source":"document-3428","target":"species-9711","weight":2},{"source":"document-3061","target":"species-9711","weight":2},{"source":"document-3080","target":"species-9711","weight":2},{"source":"document-3102","target":"species-9711","weight":2},{"source":"document-3428","target":"species-9712","weight":2},{"source":"document-3428","target":"species-9903","weight":2},{"source":"document-2876","target":"species-10042","weight":2},{"source":"document-2876","target":"species-10044","weight":2},{"source":"document-2876","target":"species-10059","weight":2},{"source":"document-2876","target":"species-10943","weight":2},{"source":"document-3102","target":"species-10943","weight":2},{"source":"document-2876","target":"species-10944","weight":2},{"source":"document-3102","target":"species-10944","weight":2},{"source":"document-2876","target":"species-10945","weight":2},{"source":"document-3102","target":"species-10945","weight":2},{"source":"document-2876","target":"species-10946","weight":2},{"source":"document-3102","target":"species-10946","weight":2},{"source":"document-2876","target":"species-10947","weight":2},{"source":"document-3102","target":"species-10947","weight":2},{"source":"document-2876","target":"species-10948","weight":2},{"source":"document-3102","target":"species-10948","weight":2},{"source":"document-2876","target":"species-10949","weight":2},{"source":"document-3102","target":"species-10949","weight":2},{"source":"document-2876","target":"species-10950","weight":2},{"source":"document-3102","target":"species-10950","weight":2},{"source":"document-2876","target":"species-10952","weight":2},{"source":"stakeholder-120","target":"document-3080","weight":2},{"source":"stakeholder-120","target":"document-3183","weight":2},{"source":"stakeholder-120","target":"document-3552","weight":2},{"source":"stakeholder-120","target":"document-3807","weight":2},{"source":"stakeholder-120","target":"document-3952","weight":2},{"source":"stakeholder-120","target":"document-3967","weight":2},{"source":"stakeholder-391","target":"document-3080","weight":2},{"source":"stakeholder-453","target":"document-2788","weight":2},{"source":"stakeholder-453","target":"document-3807","weight":2},{"source":"stakeholder-453","target":"document-3967","weight":2},{"source":"stakeholder-535","target":"document-3080","weight":2},{"source":"stakeholder-536","target":"document-3080","weight":2},{"source":"stakeholder-628","target":"document-3080","weight":2},{"source":"stakeholder-649","target":"document-2876","weight":2},{"source":"stakeholder-659","target":"document-3080","weight":2},{"source":"stakeholder-745","target":"document-3061","weight":2},{"source":"stakeholder-745","target":"document-3080","weight":2},{"source":"stakeholder-747","target":"document-3080","weight":2},{"source":"stakeholder-941","target":"document-2841","weight":2},{"source":"stakeholder-945","target":"document-3080","weight":2},{"source":"stakeholder-1032","target":"document-3552","weight":2},{"source":"stakeholder-1151","target":"document-3080","weight":2},{"source":"stakeholder-1154","target":"document-3080","weight":2},{"source":"stakeholder-1155","target":"document-3080","weight":2},{"source":"stakeholder-1435","target":"document-3967","weight":2},{"source":"author-26312","target":"document-2841","weight":6}],"meta":{"nodeCount":138,"edgeCount":504}}